{
  "domain": "brainbaking.com",
  "repositories": [
    {
      "prefix": "go-jamming",
      "subs": [
        "app",
        "app/admin",
        "app/index",
        "app/mf",
        "app/notifier",
        "app/pingback",
        "app/pingback/send",
        "app/rss",
        "app/webmention",
        "app/webmention/load",
        "app/webmention/recv",
        "app/webmention/send",
        "common",
        "db",
        "mocks",
        "rest"
      ],
      "url": "https://github.com/wgroeneveld/go-jamming"
    }
  ]
}